better_mcps_filesystem/__init__.py
better_mcps_filesystem/__main__.py
better_mcps_filesystem/server.py
better_mcps_filesystem-0.3.0.dist-info/METADATA
better_mcps_filesystem-0.3.0.dist-info/WHEEL
better_mcps_filesystem-0.3.0.dist-info/entry_points.txt
better_mcps_filesystem-0.3.0.dist-info/RECORD
