Metadata-Version: 2.4
Name: better-mcps-filesystem
Version: 0.3.0
Summary: A safe, root-scoped filesystem MCP server (FastMCP / MCP 2.0).
Author: Aron Erdelyi
License: MIT
Requires-Python: >=3.10
Requires-Dist: fastmcp>=2.0.0
Requires-Dist: pydantic>=2.0.0
